{
    "keep": {
        "days": true,
        "amount": 14
    },
    "auditLog": "D:\\Rs Mahmud\\intern-peoject\\web-developer-server\\logs\\winston\\errors\\.d711d08f522f79b8f9cfca6a9bf7a8e5311c725f-audit.json",
    "files": [
        {
            "date": 1714860202152,
            "name": "D:\\Rs Mahmud\\intern-peoject\\web-developer-server\\logs\\winston\\errors\\phu-2024-05-05-04-error.log",
            "hash": "d8531003c178b16f66abbee3fd2c03cbf31d2e860ccc511aac1cfa99ee5db9fd"
        },
        {
            "date": 1714864043922,
            "name": "D:\\Rs Mahmud\\intern-peoject\\web-developer-server\\logs\\winston\\errors\\phu-2024-05-05-05-error.log",
            "hash": "9e488fdfbc5c3e0ae563d5a0aa33beded6aae0e6f39ae9e66999352fa57af839"
        },
        {
            "date": 1714867261613,
            "name": "D:\\Rs Mahmud\\intern-peoject\\web-developer-server\\logs\\winston\\errors\\phu-2024-05-05-06-error.log",
            "hash": "bee5fe28f5ae50d0e2bd0ab4324fe950c152ecc7ef5e92922097722650ebb70b"
        },
        {
            "date": 1714872185691,
            "name": "D:\\Rs Mahmud\\intern-peoject\\web-developer-server\\logs\\winston\\errors\\phu-2024-05-05-07-error.log",
            "hash": "024862caf1c502bd8b96cf0aba9553456a71bccd2ebacebe547d9d23dc14eb4c"
        },
        {
            "date": 1714874406976,
            "name": "D:\\Rs Mahmud\\intern-peoject\\web-developer-server\\logs\\winston\\errors\\phu-2024-05-05-08-error.log",
            "hash": "b02d631df2abcb2f56d3fd59722a73a2e577c99ccb59ebe100a4e3a59985c3dc"
        }
    ],
    "hashType": "sha256"
}